rpi_7segment/__init__.py
rpi_7segment/segments.py
rpi_7segment-0.0.1.dist-info/LICENSE
rpi_7segment-0.0.1.dist-info/METADATA
rpi_7segment-0.0.1.dist-info/WHEEL
rpi_7segment-0.0.1.dist-info/top_level.txt
rpi_7segment-0.0.1.dist-info/RECORD
