Metadata-Version: 2.1
Name: rpi-7segment
Version: 0.0.1
Summary: Library for running 7-segments displays with TPIC6C596 drivers
Home-page: https://github.com/agjendem/rpi-7segment
Author: Anders Gjendem
Author-email: anders.gjendem@gmail.com
License: UNKNOWN
Platform: UNKNOWN
Classifier: Programming Language :: Python :: 3
Classifier: License :: OSI Approved :: MIT License
Classifier: Operating System :: OS Independent
Requires-Python: >=3.6
